onshape_client/__init__.py
onshape_client/apikey_headers.py
onshape_client/assembly.py
onshape_client/client.py
onshape_client/compatible_imports.py
onshape_client/onshape_rest_extras.py
onshape_client/onshape_url.py
onshape_client/units.py
onshape_client/utility.py
onshape_client/oas/__init__.py
onshape_client/oas/api_client.py
onshape_client/oas/configuration.py
onshape_client/oas/exceptions.py
onshape_client/oas/model_utils.py
onshape_client/oas/rest.py
onshape_client/oas/api/__init__.py
onshape_client/oas/api/accounts_api.py
onshape_client/oas/api/app_elements_api.py
onshape_client/oas/api/applications_api.py
onshape_client/oas/api/assemblies_api.py
onshape_client/oas/api/billing_api.py
onshape_client/oas/api/blob_elements_api.py
onshape_client/oas/api/companies_api.py
onshape_client/oas/api/default_api.py
onshape_client/oas/api/documents_api.py
onshape_client/oas/api/drawings_api.py
onshape_client/oas/api/elements_api.py
onshape_client/oas/api/feature_studios_api.py
onshape_client/oas/api/folders_api.py
onshape_client/oas/api/metadata_api.py
onshape_client/oas/api/open_api_api.py
onshape_client/oas/api/part_studios_api.py
onshape_client/oas/api/parts_api.py
onshape_client/oas/api/release_management_api.py
onshape_client/oas/api/revisions_api.py
onshape_client/oas/api/teams_api.py
onshape_client/oas/api/thumbnails_api.py
onshape_client/oas/api/translations_api.py
onshape_client/oas/api/users_api.py
onshape_client/oas/api/versions_api.py
onshape_client/oas/api/webhooks_api.py
onshape_client/oas/api/workflow_api.py
onshape_client/oas/models/__init__.py
onshape_client/oas/models/address.py
onshape_client/oas/models/api_response.py
onshape_client/oas/models/body_part.py
onshape_client/oas/models/body_part_media_type.py
onshape_client/oas/models/bt_acl_entry_info.py
onshape_client/oas/models/bt_acl_info.py
onshape_client/oas/models/bt_active_sheet_metal_filter2944.py
onshape_client/oas/models/bt_active_sheet_metal_filter2944_all_of.py
onshape_client-1.6.3.dist-info/METADATA
onshape_client-1.6.3.dist-info/WHEEL
onshape_client-1.6.3.dist-info/top_level.txt
onshape_client-1.6.3.dist-info/RECORD
