Metadata-Version: 1.2
Name: onshape_client
Version: 1.6.3
Summary: Onshape REST API
Home-page: UNKNOWN
Author-email: api-support@onshape.zendesk.com
License: UNKNOWN
Keywords: OpenAPI,OpenAPI-Generator,Onshape REST API
Platform: UNKNOWN
Requires-Python: >3.6.3
